modal_generate/cli.py
modal_generate/filter.py
modal_generate/schema.py
modal_generate/template.py
modal_generate/utils.py
modal_generate/validator.py
modal_generate-0.1.0.dist-info/LICENSE.txt
modal_generate-0.1.0.dist-info/METADATA
modal_generate-0.1.0.dist-info/WHEEL
modal_generate-0.1.0.dist-info/entry_points.txt
modal_generate-0.1.0.dist-info/RECORD
