Metadata-Version: 2.1
Name: modal-generate
Version: 0.1.0
Summary: 
Home-page: https://github.com/eliias/modal-generate
License: MIT
Keywords: modal
Author: Hannes Moser
Author-email: box@hannesmoser.at
Requires-Python: >=3.11,<4.0
Classifier: Development Status :: 1 - Planning
Classifier: Environment :: Console
Classifier: Intended Audience :: Developers
Classifier: License :: OSI Approved :: MIT License
Classifier: Operating System :: OS Independent
Classifier: Programming Language :: Python :: 3
Classifier: Programming Language :: Python :: 3.11
Classifier: Programming Language :: Python :: 3.12
Classifier: Topic :: Software Development
Classifier: Topic :: Software Development :: Libraries
Classifier: Topic :: Software Development :: Libraries :: Python Modules
Classifier: Typing :: Typed
Requires-Dist: click (>=8.1.7,<9.0.0)
Requires-Dist: jinja2 (>=3.1.3,<4.0.0)
Requires-Dist: modal (>=0.57.45,<0.58.0)
Requires-Dist: python-slugify (>=8.0.4,<9.0.0)
Requires-Dist: questionary (>=2.0.1,<3.0.0)
Requires-Dist: ruff (>=0.2.1,<0.3.0)
Project-URL: Repository, https://github.com/eliias/modal-generate
